frogml_inference/__init__.py
frogml_inference/authentication/__init__.py
frogml_inference/authentication/_login_arguments.py
frogml_inference/authentication/_utils.py
frogml_inference/authentication/authentication_utils.py
frogml_inference/authentication/constants.py
frogml_inference/batch_client/__init__.py
frogml_inference/batch_client/batch_client.py
frogml_inference/batch_client/cloud_provider_client.py
frogml_inference/batch_client/file_serialization.py
frogml_inference/batch_client/instance_validation.py
frogml_inference/batch_client/s3.py
frogml_inference/configuration/__init__.py
frogml_inference/configuration/account.py
frogml_inference/configuration/auth.py
frogml_inference/configuration/auth_config.py
frogml_inference/configuration/log_config.py
frogml_inference/configuration/session.py
frogml_inference/constants.py
frogml_inference/exceptions.py
frogml_inference/realtime_client/__init__.py
frogml_inference/realtime_client/client.py
frogml_inference/realtime_client/rest_helpers.py
frogml_inference-0.2.0.dist-info/LICENSE
frogml_inference-0.2.0.dist-info/METADATA
frogml_inference-0.2.0.dist-info/WHEEL
frogml_inference-0.2.0.dist-info/RECORD
